{
 "align_labels_right": 0,
 "creation": "2019-07-06 11:48:01.934303",
 "custom_format": 1,
 "default_print_language": "en",
 "disabled": 0,
 "doc_type": "Sales Order",
 "docstatus": 0,
 "doctype": "Print Format",
 "font": "Default",
 "html": "{% set page_width = '105mm' %}\n{% set page_height = '148mm' %}\n{% set header_height = '10mm' %}\n{% set margin_page = '5mm' %}\n{% set base_font_size = '7pt' %}\n\n{% import \"templates/includes/macros.html.j2\" as macros %}\n\n{% include \"templates/includes/pf_styles.html\" %}\n{% include \"templates/includes/optical_prescription_form.html.j2\" %}",
 "idx": 0,
 "line_breaks": 0,
 "modified": "2019-10-11 19:14:18.491985",
 "modified_by": "Administrator",
 "module": "Optic Store",
 "name": "Optical Prescription Form",
 "owner": "Administrator",
 "print_format_builder": 0,
 "print_format_type": "Server",
 "show_section_headings": 0,
 "standard": "Yes"
}